fairly/__init__.py
fairly/multimodal_analyzer.py
fairly/test.py
fairly/text_analyzer.py
fairly/models/__init__.py
fairly/models/fairly_aspects.py
fairly/models/fnd_clip.py
fairly/models/gus_net.py
fairly/models/unbias.py
the_fairly_project-0.5.dist-info/LICENSE
the_fairly_project-0.5.dist-info/METADATA
the_fairly_project-0.5.dist-info/WHEEL
the_fairly_project-0.5.dist-info/top_level.txt
the_fairly_project-0.5.dist-info/RECORD
